MANIFEST.in
README.rst
setup.py
scripts/sugar-flake
scripts/sugar-genssl
scripts/sugar-killall
scripts/sugar-lint
scripts/sugar-mkmod
scripts/sugar-valmod
sugarsack_sdk.egg-info/PKG-INFO
sugarsack_sdk.egg-info/SOURCES.txt
sugarsack_sdk.egg-info/dependency_links.txt
sugarsack_sdk.egg-info/requires.txt
sugarsack_sdk.egg-info/top_level.txt
sugarsdk/__init__.py
sugarsdk/modgen.py
sugarsdk/modval.py
sugarsdk/linting/__init__.py
sugarsdk/linting/backslashy.py
sugarsdk/linting/docstring_rstcheck.py
sugarsdk/linting/docstring_single_line.py
sugarsdk/linting/docstring_triplequotes.py
sugarsdk/linting/multireturns.py
sugarsdk/linting/pep287.py
sugarsdk/linting/pep8_emptylines.py
sugarsdk/stubs/__init__.py
sugarsdk/stubs/runner_doc.jinja2
sugarsdk/stubs/runner_examples.jinja2
sugarsdk/stubs/runner_impl.jinja2
sugarsdk/stubs/runner_init.jinja2
sugarsdk/stubs/runner_interface.jinja2
sugarsdk/stubs/runner_test.jinja2
sugarsdk/stubs/state_doc.jinja2
sugarsdk/stubs/state_examples.jinja2
sugarsdk/stubs/state_impl.jinja2
sugarsdk/stubs/state_init.jinja2